Lab02/hw_lab02/Lab2_4_bit_BLS_dataflow.v
/*
Gi = Ai'Bi
Pi = (Ai ⊕ Bi)'
Di = (Pi ⊕ Ci)'
Ci = Gi-1 + (Ci-1 ‧ Pi-1')
*/
module Lab2_4_bit_BLS_dataflow (input [3:0] A, B, input bin, output [3:0] D, output bout);

    wire [3:0] G, P, C, Q;

    assign G = (~A) & B;
    assign P = A ^ B;
    assign Q = ~P;
    assign D = P ^ C;

    assign C[0] = bin;
    assign C[1] = G[0] | (Q[0]&C[0]);
    assign C[2] = G[1] | (Q[1]&C[1]);
    assign C[3] = G[2] | (Q[2]&C[2]);
    assign bout = G[3] | (Q[3]&C[3]);

endmodule

Lab02/test.v
module	t_Lab2_4_bit_sub();

	wire	[3:0] D;
	wire	bout;
	reg		[3:0] A, B;
	reg		bin;
	
	//instantiate device under test
    //Lab2_4_bit_RBS M(A, B, bin, D, bout);
	//Lab2_4_bit_BLS_gatelevel M(A, B, bin, D, bout);
	Lab2_4_bit_BLS_dataflow M(A, B, bin, D, bout);
	//Lab2_4_bit_BLS_behavioral M(A, B, bin, D, bout);
	
	//apply inputs one at a time
	initial	begin
		A = 4'b0000; B = 4'b1100; bin = 1;
		#30 A = 4'b0001; B = 4'b0010; bin = 1;
		#30 A = 4'b0011; B = 4'b0110; bin = 1;
		#30 A = 4'b0101; B = 4'b1011; bin = 0;
		#30 A = 4'b0111; B = 4'b1010; bin = 1;
		#30 A = 4'b1000; B = 4'b0001; bin = 0;
		#30 A = 4'b1011; B = 4'b0110; bin = 0;
		#30 A = 4'b1111; B = 4'b1111; bin = 1;

	end
	initial #240 $finish;

	//dump the result of simulation
	initial begin
		$dumpfile("dataflow.vcd");
		$dumpvars;
	end
endmodule

Lab02/behavioral.vcd
$date
	Sun May  8 20:35:52 2022
$end
$version
	Icarus Verilog
$end
$timescale
	1s
$end
$scope module t_Lab2_4_bit_sub $end
$var wire 1 ! bout $end
$var wire 4 " D [3:0] $end
$var reg 4 # A [3:0] $end
$var reg 4 $ B [3:0] $end
$var reg 1 % bin $end
$scope module M $end
$var wire 4 & A [3:0] $end
$var wire 4 ' B [3:0] $end
$var wire 1 % bin $end
$var reg 4 ( C [3:0] $end
$var reg 4 ) D [3:0] $end
$var reg 4 * G [3:0] $end
$var reg 4 + P [3:0] $end
$var reg 4 , Q [3:0] $end
$var reg 1 ! bout $end
$upscope $end
$upscope $end
$enddefinitions $end
#0
$dumpvars
b11 ,
b1100 +
b1100 *
b0 )
b1111 (
b1100 '
b0 &
1%
b1100 $
b0 #
b0 "
1!
$end
#30
b1 "
b1 )
b1101 (
b1100 ,
b11 +
b10 *
b10 $
b10 '
b1 #
b1 &
#60
b11 "
b11 )
b1001 (
b1010 ,
b101 +
b100 *
b110 $
b110 '
b11 #
b11 &
#90
b101 "
b101 )
b100 (
b1 ,
b1110 +
b1010 *
0%
b1011 $
b1011 '
b101 #
b101 &
#120
b111 "
b111 )
b1 (
b10 ,
b1101 +
b1000 *
1%
b1010 $
b1010 '
b111 #
b111 &
#150
b1000 "
b1000 )
0!
b1110 (
b110 ,
b1001 +
b1 *
0%
b1 $
b1 '
b1000 #
b1000 &
#180
b1011 "
b1011 )
b1000 (
b10 ,
b1101 +
b100 *
b110 $
b110 '
b1011 #
b1011 &
#210
b1111 "
b1111 )
1!
b1111 (
b1111 ,
b0 +
b0 *
1%
b1111 $
b1111 '
b1111 #
b1111 &
