Lab02/hw_lab02/Lab2_half_sub_gatelevel.v
module Lab2_half_sub_gatelevel(input a, b, output diff, bout);

    wire w1;

	and	#(2) G3(bout, w1, b);
    not G2(w1, a);
    xor #(4) G1(diff, a, b);

endmodule

Lab02/hw_lab02/t_Lab2_half_sub.v
module	t_Lab2_half_sub();
	wire	diff, bout;
	reg		a, b;
	
	//instantiate device under test
    Lab2_half_sub_gatelevel M1(a, b, diff, bout);
	
	//apply inputs one at a time
	initial	begin
        a = 1'b0; b = 1'b0;
        #10 a = 1'b0; b = 1'b1;
        #10 a = 1'b1; b = 1'b0;
        #10 a = 1'b1; b = 1'b1;
	end
	initial #40 $finish;

	//dump the result of simulation
	initial begin
		$dumpfile("Lab2_half_sub.vcd");
		$dumpvars;
	end
endmodule

Lab02/Lab2_half_sub.vcd
$date
	Sat May  7 14:02:44 2022
$end
$version
	Icarus Verilog
$end
$timescale
	1s
$end
$scope module t_Lab2_half_sub $end
$var wire 1 ! diff $end
$var wire 1 " bout $end
$var reg 1 # a $end
$var reg 1 $ b $end
$scope module M1 $end
$var wire 1 # a $end
$var wire 1 $ b $end
$var wire 1 " bout $end
$var wire 1 ! diff $end
$var wire 1 % w1 $end
$upscope $end
$upscope $end
$enddefinitions $end
#0
$dumpvars
1%
0$
0#
x"
x!
$end
#2
0"
#4
0!
#10
1$
#12
1"
#14
1!
#20
0%
0$
1#
#22
0"
#30
1$
#34
0!
