Lab03/作業/Lab3_SR_Latch_gatelevel.v
module Lab3_SR_Latch_gatelevel (input S, R, output Q, Qb);

    wire w1, w2;
    //reg Q, Qb;
    
    wire [3:0]temp;
    nor #(10) G1(Q, R, Qb);
    nor #(10) G2(Qb, S, Q);

endmodule

Lab03/作業/t_Lab3_SR_Latch_gatelevel.v
module	t_Lab3_SR_Latch_gatelevel();
	wire	Q, Qb;
	reg		S, R;
	
	//instantiate device under test
	Lab3_SR_Latch_gatelevel M0(S, R, Q, Qb);

	//apply inputs one at a time
	initial	begin
		
        S = 1'b0; R = 1'b1;
        #30 S = 1'b1; R = 1'b0;
        #30 S = 1'b0; R = 1'b0;
        #30 S = 1'b1; R = 1'b0;
        #30 S = 1'b1; R = 1'b1;
        #50 S = 1'b0; R = 1'b0;
        #30 S = 1'b0; R = 1'b1;

	end
	initial #230 $finish;

	//dump the result of simulation
	initial begin
		$dumpfile("SR_Latch.vcd");
		$dumpvars;
	end
endmodule

Lab03/作業/SR_Latch.vcd
$date
	Mon Jun 13 21:03:48 2022
$end
$version
	Icarus Verilog
$end
$timescale
	1s
$end
$scope module t_Lab3_SR_Latch_gatelevel $end
$var wire 1 ! Qb $end
$var wire 1 " Q $end
$var reg 1 # R $end
$var reg 1 $ S $end
$scope module M0 $end
$var wire 1 " Q $end
$var wire 1 ! Qb $end
$var wire 1 # R $end
$var wire 1 $ S $end
$upscope $end
$upscope $end
$enddefinitions $end
#0
$dumpvars
0$
1#
x"
x!
$end
#10
0"
#20
1!
#30
0#
1$
#40
0!
#50
1"
#60
0$
#90
1$
#120
1#
#130
0"
#170
0#
0$
#180
1"
1!
#190
0!
0"
#200
1"
1!
1#
#210
0!
0"
#220
1!
