Lab03/作業/D_ff_AR.v
//asynchronous reset (又稱 direct reset) 之 D flip-flop 的電路模組
// active low

module D_ff_AR (input D, clock, reset, output Q);

    reg Q;

    always @(posedge clock, negedge reset)
        if(!reset) Q <= 1'b0;
        else Q <= D;

endmodule

Lab03/作業/Lab3_Sequence_Recognizer_structure.v
//電路有 reset 輸入訊號，可設定電路至初始狀態 S0 (000)
module Lab3_Sequence_Recognizer_structure (input x, clock, reset, output z);

    D_ff_AR Ma(Da, clock, reset, a);
    D_ff_AR Mb(Db, clock, reset, b);
    D_ff_AR Mc(Dc, clock, reset, c);

    wire Da, Db, Dc;
    wire a, b, c;

    assign Da = a&(~x) | (~c)&x | b&c&(~x);
    assign Db = a&b | c&x | a&c | b&(~x);
    assign Dc = (~a)&(~c)&(~x) | (~b)&(~c)&(~x) | (~a)&(~b)&(~x);
    assign z = (~a)&b&(~c)&(~x);

endmodule

Lab03/作業/Lab3_Sequence_Recognizer_state_diagram.v
module Lab3_Sequence_Recognizer_state_diagram (input x, clock, reset, output z);

    reg z;
    reg[2:0] state, next_state;
    parameter S0=3'b000, S1=3'b001, S2=3'b010,  S3=3'b011, S4=3'b100, S5=3'b101, S6=3'b110;
    
    //Form state transition-- State Register
    always @(posedge clock, negedge reset)
        if(reset==0) state <= S0; //Active-Low
        else state <= next_state;

    //Form the next state-- Next State Combinational Logic
    always @(state, x)
        case(state)
            S0: if(x) next_state = S4; else next_state = S1;
            S1: if(x) next_state = S2; else next_state = S1;
            S2: if(x) next_state = S4; else next_state = S3;
            S3: if(x) next_state = S2; else next_state = S6;
            S4: if(x) next_state = S4; else next_state = S5;
            S5: if(x) next_state = S2; else next_state = S6;
            S6: if(x) next_state = S6; else next_state = S6;
        endcase

    //Form the output-- Output Combinational Logic
    always @(state, x)
        case(state)
            S0, S1, S3, S4, S5, S6: z = 0;
            S2: z = ~x;
        endcase

endmodule

Lab03/作業/t_Lab3_Sequence_Recognizer.v
module t_Lab3_Sequence_Recognizer();
    wire	z;
	reg		x, clock, reset;
	
	//instantiate device under test
    Lab3_Sequence_Recognizer_state_diagram M0(x, clock, reset, z);
    Lab3_Sequence_Recognizer_structure M1(x, clock, reset, z);

	//Generate stimulus for clock
    initial
        begin
            clock = 0;
            reset = 0;
            #5 reset = 1;
            repeat(16)
                #5 clock = ~clock;
        end

	//Generate stimulus for x, reset
    initial 
        begin
            x = 0;
            #15 x = 1;
            repeat(8)
                #10 x = ~x;
        end

    initial #100 $finish;

	//dump the result of simulation
	initial begin
		$dumpfile("Sequence_Recognizer.vcd");
		$dumpvars;
	end

endmodule

Lab03/Sequence_Recognizer.vcd
$date
	Sun Jun 12 23:58:26 2022
$end
$version
	Icarus Verilog
$end
$timescale
	1s
$end
$scope module t_Lab3_Sequence_Recognizer $end
$var wire 1 ! z $end
$var reg 1 " clock $end
$var reg 1 # reset $end
$var reg 1 $ x $end
$scope module M0 $end
$var wire 1 " clock $end
$var wire 1 # reset $end
$var wire 1 $ x $end
$var reg 3 % next_state [2:0] $end
$var reg 3 & state [2:0] $end
$var reg 1 ' z $end
$upscope $end
$scope module M1 $end
$var wire 1 ( Da $end
$var wire 1 ) Db $end
$var wire 1 * Dc $end
$var wire 1 " clock $end
$var wire 1 # reset $end
$var wire 1 $ x $end
$var wire 1 ! z $end
$var wire 1 + c $end
$var wire 1 , b $end
$var wire 1 - a $end
$scope module Ma $end
$var wire 1 ( D $end
$var wire 1 " clock $end
$var wire 1 # reset $end
$var reg 1 - Q $end
$upscope $end
$scope module Mb $end
$var wire 1 ) D $end
$var wire 1 " clock $end
$var wire 1 # reset $end
$var reg 1 , Q $end
$upscope $end
$scope module Mc $end
$var wire 1 * D $end
$var wire 1 " clock $end
$var wire 1 # reset $end
$var reg 1 + Q $end
$upscope $end
$upscope $end
$upscope $end
$enddefinitions $end
#0
$dumpvars
0-
0,
0+
1*
0)
0(
0'
b0 &
b1 %
0$
0#
0"
0!
$end
#5
1#
#10
1+
b1 &
1"
#15
1)
0*
b10 %
0"
1$
#20
0)
1(
b100 %
b10 &
1,
0+
1"
#25
1*
0(
1)
b11 %
1!
1'
0"
0$
#30
0*
1(
0!
0'
b110 %
1+
b11 &
1"
#35
0(
1)
b10 %
0"
1$
#40
0)
1(
b100 %
b10 &
0+
1"
#45
1*
0(
1)
b11 %
1!
1'
0"
0$
#50
0*
1(
0!
0'
b110 %
1+
b11 &
1"
#55
0(
1)
b10 %
0"
1$
#60
0)
1(
b100 %
b10 &
0+
1"
#65
1*
0(
1)
b11 %
1!
1'
0"
0$
#70
0*
1(
0!
0'
b110 %
1+
b11 &
1"
#75
0(
1)
b10 %
0"
1$
#80
0)
1(
b100 %
b10 &
0+
1"
#85
1*
0(
1)
b11 %
1!
1'
0"
0$
#95
0*
1(
0)
0!
0'
b100 %
1$
